[{"topic": "Elections", "subtopic": "Other", "sentiment": 0.5, "counts": 22}, {"topic": "Health", "subtopic": "Privatization of healthcare", "sentiment": -0.6, "counts": 93}, {"topic": "Elections", "subtopic": "Election spending", "sentiment": -0.6, "counts": 111}, {"topic": "Economy", "subtopic": "Interest rates", "sentiment": -0.6, "counts": 91}, {"topic": "Energy", "subtopic": "Green energy", "sentiment": -0.8, "counts": 209}, {"topic": "Economy", "subtopic": "Other", "sentiment": 0.2, "counts": 118}, {"topic": "Media", "subtopic": "Journalism", "sentiment": -0.5, "counts": 461}, {"topic": "Tourism", "subtopic": "Other", "sentiment": -0.5, "counts": 319}, {"topic": "Migration", "subtopic": "Other", "sentiment": -0.6, "counts": 361}, {"topic": "Migration", "subtopic": "Other", "sentiment": -0.2356, "counts": 454}, {"topic": "Migration", "subtopic": "Other", "sentiment": 0.0, "counts": 112}, {"topic": "Corruption", "subtopic": "Tax evasion", "sentiment": -0.6, "counts": 194}, {"topic": "Energy", "subtopic": "Other", "sentiment": -0.8, "counts": 124}, {"topic": "Elections", "subtopic": "Election spending", "sentiment": 0.4, "counts": 107}]