[{"topic": "Elections", "counts": 863, "freq": 0.43807106598984774}, {"topic": "Health", "counts": 446, "freq": 0.2263959390862944}, {"topic": "Migration", "counts": 336, "freq": 0.17055837563451776}, {"topic": "Employment", "counts": 125, "freq": 0.06345177664974619}, {"topic": "Tourism", "counts": 57, "freq": 0.028934010152284265}, {"topic": "Environment", "counts": 44, "freq": 0.02233502538071066}, {"topic": "Agricultural policy", "counts": 39, "freq": 0.01979695431472081}, {"topic": "Civil protection", "counts": 27, "freq": 0.013705583756345178}, {"topic": "Other", "counts": 33, "freq": 0.016751269035532996}]