[{"topic": "Economy", "counts": 815, "freq": 0.29411764705882354}, {"topic": "Elections", "counts": 531, "freq": 0.19162757127390834}, {"topic": "Health", "counts": 465, "freq": 0.1678094550703717}, {"topic": "Corruption", "counts": 237, "freq": 0.08552869000360881}, {"topic": "Democracy", "counts": 148, "freq": 0.0534103211836882}, {"topic": "Employment", "counts": 134, "freq": 0.048357993504150126}, {"topic": "Housing", "counts": 130, "freq": 0.04691447130999639}, {"topic": "Debt", "counts": 119, "freq": 0.04294478527607362}, {"topic": "Social state", "counts": 78, "freq": 0.028148682785997834}, {"topic": "National security", "counts": 67, "freq": 0.024178996752075063}, {"topic": "Agricultural policy", "counts": 47, "freq": 0.016961385781306387}]