[{"topic": "Elections", "subtopic": "Election spending", "counts": 555, "freq": 0.1129656014654997}, {"topic": "Elections", "subtopic": "Cost of living", "counts": 177, "freq": 0.036026867494402606}, {"topic": "Elections", "subtopic": "Other", "counts": 1357, "freq": 0.2762059841237533}, {"topic": "Economy", "subtopic": "Economic crisis", "counts": 134, "freq": 0.027274577651129655}, {"topic": "Economy", "subtopic": "Other", "counts": 468, "freq": 0.09525748015469164}, {"topic": "Transparency", "subtopic": "Other", "counts": 433, "freq": 0.08813352330551598}, {"topic": "Health", "subtopic": "Public health system", "counts": 222, "freq": 0.045186240586199876}, {"topic": "Employment", "subtopic": "Workers' rights", "counts": 54, "freq": 0.010991247710156728}, {"topic": "Employment", "subtopic": "Other", "counts": 157, "freq": 0.031956035009159375}, {"topic": "Education", "subtopic": "Higher education", "counts": 197, "freq": 0.04009769997964584}, {"topic": "Debt", "subtopic": "Bank regulations", "counts": 161, "freq": 0.03277020150620802}, {"topic": "Agricultural policy", "subtopic": "Other", "counts": 159, "freq": 0.0323631182576837}, {"topic": "Energy", "subtopic": "Green energy", "counts": 134, "freq": 0.027274577651129655}, {"topic": "External affairs", "subtopic": "Other", "counts": 134, "freq": 0.027274577651129655}, {"topic": "Social state", "subtopic": "None", "counts": 119, "freq": 0.02422145328719723}, {"topic": "Europe", "subtopic": "European recovery fund", "counts": 119, "freq": 0.02422145328719723}, {"topic": "Migration", "subtopic": "Other", "counts": 111, "freq": 0.022593120293099938}, {"topic": "Housing", "subtopic": "Other", "counts": 102, "freq": 0.020761245674740483}, {"topic": "Democracy", "subtopic": "Wiretapping", "counts": 74, "freq": 0.015062080195399959}, {"topic": "Pensioners", "subtopic": "Pensions", "counts": 46, "freq": 0.009362914716059434}]