[{"topic": "Economy", "counts": 863, "freq": 0.176518715483739}, {"topic": "Elections", "counts": 760, "freq": 0.15545101247698917}, {"topic": "Energy", "counts": 622, "freq": 0.1272243812640622}, {"topic": "Democracy", "counts": 403, "freq": 0.08242994477398241}, {"topic": "Housing", "counts": 270, "freq": 0.0552260175905093}, {"topic": "Education", "counts": 224, "freq": 0.045817140519533645}, {"topic": "Employment", "counts": 173, "freq": 0.03538555941910411}, {"topic": "Health", "counts": 171, "freq": 0.03497647780732256}, {"topic": "Public sector", "counts": 122, "freq": 0.024953978318674574}, {"topic": "Accountability", "counts": 64, "freq": 0.013090611577009614}, {"topic": "Other", "counts": 1217, "freq": 0.24892616076907342}]