[{"topic": "Employment", "subtopic": "Workers' rights", "sentiment": 0.8, "counts": 449}, {"topic": "Elections", "subtopic": "Election spending", "sentiment": -0.7, "counts": 131}, {"topic": "Economy", "subtopic": "Other", "sentiment": -0.4, "counts": 202}, {"topic": "Media", "subtopic": "Press freedom", "sentiment": -0.5, "counts": 80}, {"topic": "Health", "subtopic": "Other", "sentiment": -0.8, "counts": 52}, {"topic": "Elections", "subtopic": "Abstention", "sentiment": -0.6, "counts": 73}, {"topic": "Other", "subtopic": "Other", "sentiment": -0.6, "counts": 231}, {"topic": "Elections", "subtopic": "European recovery fund", "sentiment": -0.9, "counts": 157}, {"topic": "Elections", "subtopic": "Other", "sentiment": 0.0, "counts": 228}, {"topic": "Agricultural policy", "subtopic": "Other", "sentiment": -0.6, "counts": 207}, {"topic": "Elections", "subtopic": "Abstention", "sentiment": 0.7, "counts": 84}, {"topic": "Democracy", "subtopic": "Other", "sentiment": -0.2, "counts": 118}, {"topic": "Elections", "subtopic": "Working class", "sentiment": 0.8, "counts": 219}, {"topic": "National security", "subtopic": "Other", "sentiment": -0.9, "counts": 178}, {"topic": "Other", "subtopic": "Election spending", "sentiment": 0.7, "counts": 97}, {"topic": "Elections", "subtopic": "Election spending", "sentiment": 0.0, "counts": 277}, {"topic": "Elections", "subtopic": "Election spending", "sentiment": 0.6, "counts": 345}]