[{"speech": "Koutsoumpas_2023_04_27_Lesvos", "topic": "Elections", "sentiment": -0.1865348980852378, "sentiment-label": "neutral"}, {"speech": "Koutsoumpas_2023_04_27_Lesvos", "topic": "Environment", "sentiment": -0.9000000000000001, "sentiment-label": "negative"}, {"speech": "Koutsoumpas_2023_04_27_Lesvos", "topic": "Employment", "sentiment": -0.8, "sentiment-label": "negative"}, {"speech": "Koutsoumpas_2023_04_27_Lesvos", "topic": "Economy", "sentiment": -0.2534965034965035, "sentiment-label": "neutral"}, {"speech": "Koutsoumpas_2023_04_27_Lesvos", "topic": "External affairs", "sentiment": -0.49921874999999993, "sentiment-label": "negative"}, {"speech": "Koutsoumpas_2023_04_27_Lesvos", "topic": "Migration", "sentiment": -0.20970350404312668, "sentiment-label": "neutral"}, {"speech": "Koutsoumpas_2023_04_27_Lesvos", "topic": "Accountability", "sentiment": -0.6, "sentiment-label": "negative"}, {"speech": "Koutsoumpas_2023_04_27_Lesvos", "topic": "Health", "sentiment": -0.7382425742574258, "sentiment-label": "negative"}, {"speech": "Koutsoumpas_2023_04_27_Lesvos", "topic": "Corruption", "sentiment": -0.5, "sentiment-label": "negative"}, {"speech": "Koutsoumpas_2023_04_27_Lesvos", "topic": "Civil protection", "sentiment": -0.4, "sentiment-label": "negative"}, {"speech": "Koutsoumpas_2023_04_30_Kaisariani", "topic": "Culture", "sentiment": 0.11205179282868526, "sentiment-label": "neutral"}, {"speech": "Koutsoumpas_2023_04_30_Kaisariani", "topic": "Economy", "sentiment": -0.6861442786069651, "sentiment-label": "negative"}, {"speech": "Koutsoumpas_2023_04_30_Kaisariani", "topic": "Corruption", "sentiment": -0.7999999999999999, "sentiment-label": "negative"}, {"speech": "Koutsoumpas_2023_04_30_Kaisariani", "topic": "Employment", "sentiment": -0.25435667752443, "sentiment-label": "neutral"}, {"speech": "Koutsoumpas_2023_04_30_Kaisariani", "topic": "Accountability", "sentiment": 0.5, "sentiment-label": "positive"}, {"speech": "Koutsoumpas_2023_04_30_Kaisariani", "topic": "Europe", "sentiment": -0.33781512605042013, "sentiment-label": "negative"}, {"speech": "Koutsoumpas_2023_04_30_Kaisariani", "topic": "Social state", "sentiment": -1.0, "sentiment-label": "negative"}, {"speech": "Koutsoumpas_2023_04_30_Kaisariani", "topic": "Elections", "sentiment": 0.10157068062827225, "sentiment-label": "neutral"}, {"speech": "Koutsoumpas_2023_04_30_Kaisariani", "topic": "Housing", "sentiment": -0.5, "sentiment-label": "negative"}, {"speech": "Koutsoumpas_2023_04_30_Kaisariani", "topic": "Other", "sentiment": 0.4000000000000001, "sentiment-label": "positive"}, {"speech": "Koutsoumpas_2023_04_30_Kaisariani", "topic": "Education", "sentiment": 0.5, "sentiment-label": "positive"}, {"speech": "Koutsoumpas_2023_04_30_Kaisariani", "topic": "Democracy", "sentiment": 0.75, "sentiment-label": "positive"}, {"speech": "Koutsoumpas_2023_05_04_Ioannina", "topic": "Elections", "sentiment": 0.08762414056531705, "sentiment-label": "neutral"}, {"speech": "Koutsoumpas_2023_05_04_Ioannina", "topic": "Other", "sentiment": 0.509322033898305, "sentiment-label": "positive"}, {"speech": "Koutsoumpas_2023_05_04_Ioannina", "topic": "Privatization", "sentiment": -0.32783505154639175, "sentiment-label": "neutral"}, {"speech": "Koutsoumpas_2023_05_04_Ioannina", "topic": "Health", "sentiment": -0.7768168604651163, "sentiment-label": "negative"}, {"speech": "Koutsoumpas_2023_05_04_Ioannina", "topic": "Pandemic", "sentiment": -0.7, "sentiment-label": "negative"}, {"speech": "Koutsoumpas_2023_05_04_Ioannina", "topic": "Economy", "sentiment": -0.8, "sentiment-label": "negative"}, {"speech": "Koutsoumpas_2023_05_04_Ioannina", "topic": "Corruption", "sentiment": -0.8, "sentiment-label": "negative"}, {"speech": "Koutsoumpas_2023_05_05_Larisa", "topic": "Elections", "sentiment": 0.005120481927710852, "sentiment-label": "neutral"}, {"speech": "Koutsoumpas_2023_05_05_Larisa", "topic": "Other", "sentiment": -0.6966183574879227, "sentiment-label": "negative"}, {"speech": "Koutsoumpas_2023_05_05_Larisa", "topic": "Economy", "sentiment": -0.7999999999999999, "sentiment-label": "negative"}, {"speech": "Koutsoumpas_2023_05_05_Larisa", "topic": "Employment", "sentiment": 0.5, "sentiment-label": "positive"}, {"speech": "Koutsoumpas_2023_05_05_Larisa", "topic": "Pandemic", "sentiment": -0.6, "sentiment-label": "negative"}, {"speech": "Koutsoumpas_2023_05_05_Larisa", "topic": "Energy", "sentiment": -0.7392592592592594, "sentiment-label": "negative"}, {"speech": "Koutsoumpas_2023_05_05_Larisa", "topic": "Agricultural policy", "sentiment": -0.9, "sentiment-label": "negative"}, {"speech": "Koutsoumpas_2023_05_05_Larisa", "topic": "External affairs", "sentiment": -0.6506510416666668, "sentiment-label": "negative"}, {"speech": "Koutsoumpas_2023_05_05_Larisa", "topic": "National security", "sentiment": -0.9000000000000001, "sentiment-label": "negative"}, {"speech": "Koutsoumpas_2023_05_05_Larisa", "topic": "Infrastructure", "sentiment": -0.5849514563106796, "sentiment-label": "negative"}, {"speech": "Koutsoumpas_2023_05_05_Larisa", "topic": "Privatization", "sentiment": -0.8163179916317993, "sentiment-label": "negative"}, {"speech": "Koutsoumpas_2023_05_05_Larisa", "topic": "Accountability", "sentiment": 0.5, "sentiment-label": "positive"}, {"speech": "Koutsoumpas_2023_05_06_Aigaleo", "topic": "Elections", "sentiment": -0.5177076625885383, "sentiment-label": "negative"}, {"speech": "Koutsoumpas_2023_05_06_Aigaleo", "topic": "Democracy", "sentiment": -0.38699654775604153, "sentiment-label": "negative"}, {"speech": "Koutsoumpas_2023_05_06_Aigaleo", "topic": "Economy", "sentiment": -0.6795660036166364, "sentiment-label": "negative"}, {"speech": "Koutsoumpas_2023_05_06_Aigaleo", "topic": "Employment", "sentiment": -0.671, "sentiment-label": "negative"}, {"speech": "Koutsoumpas_2023_05_06_Aigaleo", "topic": "Other", "sentiment": 0.5, "sentiment-label": "positive"}, {"speech": "Koutsoumpas_2023_05_07_Ekdilosi_Gazi", "topic": "Housing", "sentiment": -0.40331186752529896, "sentiment-label": "negative"}, {"speech": "Koutsoumpas_2023_05_07_Ekdilosi_Gazi", "topic": "Tourism", "sentiment": 0.0, "sentiment-label": "neutral"}, {"speech": "Koutsoumpas_2023_05_07_Ekdilosi_Gazi", "topic": "Economy", "sentiment": -0.8868778280542986, "sentiment-label": "negative"}, {"speech": "Koutsoumpas_2023_05_07_Ekdilosi_Gazi", "topic": "Debt", "sentiment": -0.813237639553429, "sentiment-label": "negative"}, {"speech": "Koutsoumpas_2023_05_07_Ekdilosi_Gazi", "topic": "Infrastructure", "sentiment": -0.8504048582995952, "sentiment-label": "negative"}, {"speech": "Koutsoumpas_2023_05_07_Ekdilosi_Gazi", "topic": "Other", "sentiment": -0.005112474437627812, "sentiment-label": "neutral"}, {"speech": "Koutsoumpas_2023_05_07_Ekdilosi_Gazi", "topic": "Elections", "sentiment": 0.0, "sentiment-label": "neutral"}, {"speech": "Koutsoumpas_2023_05_09_Kallithea", "topic": "Democracy", "sentiment": -0.8000000000000002, "sentiment-label": "negative"}, {"speech": "Koutsoumpas_2023_05_09_Kallithea", "topic": "Other", "sentiment": -0.2, "sentiment-label": "neutral"}, {"speech": "Koutsoumpas_2023_05_09_Kallithea", "topic": "Elections", "sentiment": 0.09712017094017095, "sentiment-label": "neutral"}, {"speech": "Koutsoumpas_2023_05_09_Kallithea", "topic": "Housing", "sentiment": -0.5, "sentiment-label": "negative"}, {"speech": "Koutsoumpas_2023_05_09_Kallithea", "topic": "Economy", "sentiment": -0.48628673196794303, "sentiment-label": "negative"}, {"speech": "Koutsoumpas_2023_05_09_Kallithea", "topic": "Pandemic", "sentiment": -0.4, "sentiment-label": "negative"}, {"speech": "Koutsoumpas_2023_05_09_Kallithea", "topic": "Employment", "sentiment": 0.1, "sentiment-label": "neutral"}, {"speech": "Koutsoumpas_2023_05_12_Lamia", "topic": "Elections", "sentiment": -0.003763736263736276, "sentiment-label": "neutral"}, {"speech": "Koutsoumpas_2023_05_12_Lamia", "topic": "Economy", "sentiment": -0.27909238249594814, "sentiment-label": "neutral"}, {"speech": "Koutsoumpas_2023_05_12_Lamia", "topic": "Accountability", "sentiment": -0.5, "sentiment-label": "negative"}, {"speech": "Koutsoumpas_2023_05_12_Lamia", "topic": "Housing", "sentiment": -0.16380090497737557, "sentiment-label": "neutral"}, {"speech": "Koutsoumpas_2023_05_12_Lamia", "topic": "Other", "sentiment": -0.8, "sentiment-label": "negative"}, {"speech": "Koutsoumpas_2023_05_12_Lamia", "topic": "Agricultural policy", "sentiment": -0.158, "sentiment-label": "neutral"}, {"speech": "Koutsoumpas_2023_05_12_Lamia", "topic": "Civil protection", "sentiment": 0.3, "sentiment-label": "neutral"}, {"speech": "Koutsoumpas_2023_05_12_Lamia", "topic": "Democracy", "sentiment": 0.3884146341463415, "sentiment-label": "positive"}, {"speech": "Koutsoumpas_2023_05_12_Lamia", "topic": "Health", "sentiment": 0.0, "sentiment-label": "neutral"}, {"speech": "Koutsoumpas_2023_05_12_Lamia", "topic": "Infrastructure", "sentiment": 0.8, "sentiment-label": "positive"}, {"speech": "Koutsoumpas_2023_05_12_Lamia", "topic": "Environment", "sentiment": 0.3, "sentiment-label": "neutral"}, {"speech": "Koutsoumpas_2023_05_13_Heraklion", "topic": "Elections", "sentiment": -0.1328947368421053, "sentiment-label": "neutral"}, {"speech": "Koutsoumpas_2023_05_13_Heraklion", "topic": "Economy", "sentiment": -0.285342019543974, "sentiment-label": "neutral"}, {"speech": "Koutsoumpas_2023_05_13_Heraklion", "topic": "Energy", "sentiment": -0.5, "sentiment-label": "negative"}, {"speech": "Koutsoumpas_2023_05_13_Heraklion", "topic": "Housing", "sentiment": -0.6686567164179104, "sentiment-label": "negative"}, {"speech": "Koutsoumpas_2023_05_13_Heraklion", "topic": "External affairs", "sentiment": -0.6338308457711442, "sentiment-label": "negative"}, {"speech": "Koutsoumpas_2023_05_13_Heraklion", "topic": "Tourism", "sentiment": -0.5804444444444444, "sentiment-label": "negative"}, {"speech": "Koutsoumpas_2023_05_13_Heraklion", "topic": "Employment", "sentiment": -0.5136919315403423, "sentiment-label": "negative"}, {"speech": "Koutsoumpas_2023_05_13_Heraklion", "topic": "Infrastructure", "sentiment": 0.04367346938775511, "sentiment-label": "neutral"}, {"speech": "Koutsoumpas_2023_05_13_Heraklion", "topic": "Social state", "sentiment": -0.4, "sentiment-label": "negative"}, {"speech": "Koutsoumpas_2023_05_13_Heraklion", "topic": "Health", "sentiment": -0.9, "sentiment-label": "negative"}, {"speech": "Koutsoumpas_2023_05_13_Heraklion", "topic": "Democracy", "sentiment": 1.0, "sentiment-label": "positive"}, {"speech": "Koutsoumpas_2023_05_15_Thessaloniki", "topic": "Elections", "sentiment": 0.07302107728337237, "sentiment-label": "neutral"}, {"speech": "Koutsoumpas_2023_05_15_Thessaloniki", "topic": "Employment", "sentiment": -1.0, "sentiment-label": "negative"}, {"speech": "Koutsoumpas_2023_05_15_Thessaloniki", "topic": "External affairs", "sentiment": -0.7, "sentiment-label": "negative"}, {"speech": "Koutsoumpas_2023_05_15_Thessaloniki", "topic": "Economy", "sentiment": -0.7033813747228382, "sentiment-label": "negative"}, {"speech": "Koutsoumpas_2023_05_15_Thessaloniki", "topic": "Other", "sentiment": 0.0, "sentiment-label": "neutral"}, {"speech": "Koutsoumpas_2023_05_15_Thessaloniki", "topic": "Housing", "sentiment": 0.0, "sentiment-label": "neutral"}, {"speech": "Koutsoumpas_2023_05_15_Thessaloniki", "topic": "Democracy", "sentiment": -0.8, "sentiment-label": "negative"}, {"speech": "Koutsoumpas_2023_05_16_Patra", "topic": "Elections", "sentiment": 0.10073076923076922, "sentiment-label": "neutral"}, {"speech": "Koutsoumpas_2023_05_16_Patra", "topic": "Other", "sentiment": -0.9, "sentiment-label": "negative"}, {"speech": "Koutsoumpas_2023_05_16_Patra", "topic": "Economy", "sentiment": -0.5493693693693693, "sentiment-label": "negative"}, {"speech": "Koutsoumpas_2023_05_16_Patra", "topic": "National security", "sentiment": -0.8, "sentiment-label": "negative"}, {"speech": "Koutsoumpas_2023_05_16_Patra", "topic": "Employment", "sentiment": 0.5196774193548387, "sentiment-label": "positive"}, {"speech": "Koutsoumpas_2023_05_16_Patra", "topic": "External affairs", "sentiment": 0.5, "sentiment-label": "positive"}, {"speech": "Koutsoumpas_2023_05_16_Patra", "topic": "Democracy", "sentiment": -0.8, "sentiment-label": "negative"}]