[{"topic": "Accountability", "counts": 551, "freq": 0.21143514965464313}, {"topic": "Economy", "counts": 269, "freq": 0.1032233307751343}, {"topic": "Elections", "counts": 254, "freq": 0.09746738296239447}, {"topic": "Democracy", "counts": 252, "freq": 0.09669992325402917}, {"topic": "Debt", "counts": 185, "freq": 0.07099002302379125}, {"topic": "Employment", "counts": 161, "freq": 0.06178050652340752}, {"topic": "External affairs", "counts": 78, "freq": 0.029930928626247123}, {"topic": "Europe", "counts": 21, "freq": 0.008058326937835763}, {"topic": "Other", "counts": 835, "freq": 0.32041442824251726}]