[{"topic": "Migration", "subtopic": "Other", "counts": 856, "freq": 0.17075603431079195}, {"topic": "Environment", "subtopic": "Green energy", "counts": 65, "freq": 0.012966287652104528}, {"topic": "Environment", "subtopic": "Other", "counts": 472, "freq": 0.09415519648912826}, {"topic": "Accountability", "subtopic": "Other", "counts": 535, "freq": 0.10672252144424496}, {"topic": "Democracy", "subtopic": "Other", "counts": 425, "freq": 0.08477957310991423}, {"topic": "Employment", "subtopic": "Youth", "counts": 274, "freq": 0.05465788948733293}, {"topic": "Employment", "subtopic": "Maternity leave", "counts": 113, "freq": 0.022541392379812487}, {"topic": "Education", "subtopic": "Other", "counts": 342, "freq": 0.06822262118491922}, {"topic": "Public sector", "subtopic": "Other", "counts": 324, "freq": 0.06463195691202872}, {"topic": "Elections", "subtopic": "Other", "counts": 252, "freq": 0.05026929982046679}, {"topic": "Economy", "subtopic": "Other", "counts": 234, "freq": 0.0466786355475763}, {"topic": "Corruption", "subtopic": "Oligarchy", "counts": 141, "freq": 0.028126870137642132}, {"topic": "Tourism", "subtopic": "Other", "counts": 113, "freq": 0.022541392379812487}, {"topic": "Entrepreneurship", "subtopic": "Investments", "counts": 97, "freq": 0.019349690803909834}, {"topic": "Infrastructure", "subtopic": "Green energy", "counts": 70, "freq": 0.013963694394574106}, {"topic": "Agricultural policy", "subtopic": "Other", "counts": 57, "freq": 0.011370436864153202}, {"topic": "Human rights", "subtopic": "Other", "counts": 32, "freq": 0.006383403151805306}, {"topic": "Other", "subtopic": "Affordable housing", "counts": 292, "freq": 0.05824855376022342}, {"topic": "Other", "subtopic": "Youth", "counts": 197, "freq": 0.039297825653301414}, {"topic": "Other", "subtopic": "Other", "counts": 122, "freq": 0.02433672451625773}]