{"name": "Tsipras,Giannitsa,2023-06-17", "value": 210, "children": [{"name": "Locations", "value": 17, "children": [{"name": "Giannitsa", "value": 2}, {"name": "Pella", "value": 5}, {"name": "Edessa", "value": 1}, {"name": "Rural Areas", "value": 1}, {"name": "House", "value": 2}, {"name": "Europe", "value": 2}, {"name": "Thrace", "value": 2}, {"name": "Muslim Minority", "value": 1}, {"name": "Iasmo", "value": 1}]}, {"name": "Political parties", "value": 15, "children": [{"name": "SYRIZA", "value": 7}, {"name": "New Democracy", "value": 7}, {"name": "Democrat", "value": 1}]}, {"name": "Groups of people", "value": 75, "children": [{"name": "Greek People", "value": 3}, {"name": "Greek Society", "value": 2}, {"name": "Political Opponents", "value": 1}, {"name": "Communications War", "value": 1}, {"name": "Society", "value": 4}, {"name": "Households", "value": 1}, {"name": "Producers", "value": 3}, {"name": "Farmers", "value": 4}, {"name": "Public Hospitals", "value": 1}, {"name": "Substitutes", "value": 1}, {"name": "Young People", "value": 1}, {"name": "Benefits", "value": 1}, {"name": "Handouts", "value": 1}, {"name": "Weather Conditions", "value": 1}, {"name": "Individuals", "value": 1}, {"name": "Producer", "value": 1}, {"name": "Middle-class Households", "value": 1}, {"name": "Five Political Leaders", "value": 1}, {"name": "Public Interest", "value": 1}, {"name": "Doctors", "value": 3}, {"name": "Nurses", "value": 3}, {"name": "Citizen", "value": 1}, {"name": "Primary Care Doctors", "value": 1}, {"name": "Scientists", "value": 1}, {"name": "Thirteen Large Business Groups", "value": 1}, {"name": "Small And Medium Enterprises", "value": 1}, {"name": "Health", "value": 1}, {"name": "Agriculture", "value": 1}, {"name": "Small And Medium-sized Entrepreneurship", "value": 1}, {"name": "People Of Creation", "value": 1}, {"name": "Underprivileged", "value": 1}, {"name": "Tsunami", "value": 1}, {"name": "Foreclosures", "value": 1}, {"name": "Haircut", "value": 1}, {"name": "Nominal Value Of The Loan", "value": 1}, {"name": "Installments", "value": 1}, {"name": "Middle Class", "value": 1}, {"name": "Professional Housing", "value": 1}, {"name": "Agricultural Land", "value": 1}, {"name": "Greek Citizen", "value": 1}, {"name": "Farmer", "value": 1}, {"name": "Small And Medium-sized", "value": 1}, {"name": "Young", "value": 1}, {"name": "Old", "value": 1}, {"name": "Worker", "value": 1}, {"name": "Employee", "value": 1}, {"name": "Right-wing", "value": 1}, {"name": "Venizelists", "value": 1}, {"name": "Anti-venizelists", "value": 1}, {"name": "Muslim Minority", "value": 1}, {"name": "Turks Of Western Thrace", "value": 1}, {"name": "Every Social Group", "value": 1}, {"name": "Family", "value": 1}, {"name": "Progressive Citizen", "value": 1}, {"name": "Good Strength", "value": 1}, {"name": "Good Power", "value": 1}, {"name": "Values", "value": 1}, {"name": "Ideas", "value": 1}, {"name": "Ideals", "value": 1}, {"name": "Underprivileged Citizens", "value": 1}]}, {"name": "Dates", "value": 21, "children": [{"name": "June 25th", "value": 3}, {"name": "Sunday", "value": 1}, {"name": "Third Week", "value": 1}, {"name": "'21", "value": 1}, {"name": "'22", "value": 1}, {"name": "'23", "value": 1}, {"name": "600", "value": 1}, {"name": "2009", "value": 1}, {"name": "2015", "value": 1}, {"name": "40 Billion Euros", "value": 1}, {"name": "Million", "value": 1}, {"name": "Pandemic", "value": 1}, {"name": "2019", "value": 1}, {"name": "2023", "value": 1}, {"name": "2020", "value": 1}, {"name": "'18", "value": 1}, {"name": "Medium-term Plan", "value": 1}, {"name": "The Next Four Years", "value": 1}, {"name": "Four Years", "value": 1}]}, {"name": "Organizations", "value": 52, "children": [{"name": "Media", "value": 1}, {"name": "Familiar Old System", "value": 1}, {"name": "50 Bonus Seats", "value": 1}, {"name": "Income Inequality", "value": 1}, {"name": "Society", "value": 1}, {"name": "Electricity Bills", "value": 1}, {"name": "National Health System", "value": 9}, {"name": "Universities", "value": 1}, {"name": "Economy", "value": 1}, {"name": "Elga", "value": 3}, {"name": "Peach Producers", "value": 1}, {"name": "Cherry Producers", "value": 1}, {"name": "State", "value": 3}, {"name": "Elga Regulation", "value": 1}, {"name": "Community Funds", "value": 1}, {"name": "State Budget", "value": 1}, {"name": "Ministry Of Rural Development", "value": 1}, {"name": "Commission", "value": 1}, {"name": "European Commission", "value": 1}, {"name": "Energy Cartels", "value": 1}, {"name": "Refining Cartels", "value": 1}, {"name": "Supply Chain Cartels", "value": 1}, {"name": "European Union", "value": 1}, {"name": "Excise Tax", "value": 1}, {"name": "Troika", "value": 1}, {"name": "Health Units", "value": 1}, {"name": "Recovery And Resilience Fund", "value": 1}, {"name": "Social Security Funds", "value": 1}, {"name": "Systemic Banks", "value": 1}, {"name": "Recovery Fund", "value": 2}, {"name": "Central Banks", "value": 1}, {"name": "Justice", "value": 1}, {"name": "Regulatory Framework", "value": 1}, {"name": "Mandatory Settlements", "value": 1}, {"name": "Out-of-court Mechanism", "value": 1}, {"name": "Turkish Media", "value": 1}, {"name": "Turkish Government", "value": 1}, {"name": "Regime", "value": 1}, {"name": "Party", "value": 1}]}, {"name": "Persons", "value": 24, "children": [{"name": "Mitsotakis", "value": 12}, {"name": "Young People", "value": 1}, {"name": "Farmer", "value": 1}, {"name": "Farmers", "value": 1}, {"name": "Mr Samaras", "value": 1}, {"name": "Mr. Pneumatikos", "value": 1}, {"name": "Human Life", "value": 1}, {"name": "Pissarides", "value": 1}, {"name": "Mr. Pneimatikos", "value": 1}, {"name": "Mr. Katradzi", "value": 1}, {"name": "Erdogan", "value": 2}, {"name": "Mrs Bakoyannis", "value": 1}]}, {"name": "Countries", "value": 6, "children": [{"name": "Greece", "value": 3}, {"name": "Slovakia", "value": 1}, {"name": "Malta", "value": 1}, {"name": "Turkey", "value": 1}]}]}