[{"topic": "Elections", "subtopic": "Working class", "counts": 575, "freq": 0.17118189937481393}, {"topic": "Elections", "subtopic": "Election spending", "counts": 487, "freq": 0.14498362607919024}, {"topic": "Elections", "subtopic": "Other", "counts": 500, "freq": 0.14885382554331647}, {"topic": "Democracy", "subtopic": "Other", "counts": 285, "freq": 0.08484668055969039}, {"topic": "Pensioners", "subtopic": "Pensions", "counts": 261, "freq": 0.07770169693361119}, {"topic": "Economy", "subtopic": "Other", "counts": 159, "freq": 0.04733551652277464}, {"topic": "Health", "subtopic": "Privatization of healthcare", "counts": 96, "freq": 0.02857993450431676}, {"topic": "Health", "subtopic": "Public health system", "counts": 46, "freq": 0.013694551949985114}, {"topic": "Housing", "subtopic": "Affordable housing", "counts": 28, "freq": 0.008335814230425722}, {"topic": "Housing", "subtopic": "Other", "counts": 92, "freq": 0.027389103899970228}, {"topic": "Employment", "subtopic": "Working class", "counts": 54, "freq": 0.016076213158678177}, {"topic": "Employment", "subtopic": "Other", "counts": 61, "freq": 0.01816016671628461}, {"topic": "Education", "subtopic": "Higher education", "counts": 42, "freq": 0.012503721345638583}, {"topic": "Education", "subtopic": "Employment", "counts": 34, "freq": 0.01012206013694552}, {"topic": "Debt", "subtopic": "Austerity", "counts": 37, "freq": 0.011015183090205419}, {"topic": "Energy", "subtopic": "Electricity", "counts": 31, "freq": 0.00922893718368562}, {"topic": "Infrastructure", "subtopic": "Other", "counts": 27, "freq": 0.008038106579339089}, {"topic": "External affairs", "subtopic": "Other", "counts": 17, "freq": 0.00506103006847276}, {"topic": "Other", "subtopic": "Working class", "counts": 98, "freq": 0.029175349806490027}, {"topic": "Other", "subtopic": "Other", "counts": 429, "freq": 0.12771658231616553}]