[{"topic": "Agricultural policy", "counts": 513, "freq": 0.13849892008639308}, {"topic": "Education", "counts": 429, "freq": 0.1158207343412527}, {"topic": "External affairs", "counts": 387, "freq": 0.10448164146868251}, {"topic": "Democracy", "counts": 365, "freq": 0.09854211663066954}, {"topic": "Health", "counts": 271, "freq": 0.07316414686825054}, {"topic": "Elections", "counts": 265, "freq": 0.07154427645788337}, {"topic": "Economy", "counts": 223, "freq": 0.060205183585313175}, {"topic": "Privatization", "counts": 208, "freq": 0.056155507559395246}, {"topic": "Energy", "counts": 188, "freq": 0.05075593952483801}, {"topic": "Housing", "counts": 149, "freq": 0.040226781857451405}, {"topic": "Migration", "counts": 117, "freq": 0.031587473002159826}, {"topic": "Social state", "counts": 94, "freq": 0.025377969762419007}, {"topic": "Other", "counts": 495, "freq": 0.13363930885529157}]