[{"topic": "Privatization", "counts": 524, "freq": 0.24014665444546288}, {"topic": "Economy", "counts": 378, "freq": 0.17323556370302476}, {"topic": "Media", "counts": 210, "freq": 0.09624197983501374}, {"topic": "Democracy", "counts": 189, "freq": 0.08661778185151238}, {"topic": "Corruption", "counts": 187, "freq": 0.08570119156736938}, {"topic": "Pensioners", "counts": 159, "freq": 0.07286892758936755}, {"topic": "National security", "counts": 124, "freq": 0.05682859761686526}, {"topic": "Europe", "counts": 105, "freq": 0.04812098991750687}, {"topic": "Elections", "counts": 61, "freq": 0.027956003666361137}, {"topic": "Entrepreneurship", "counts": 50, "freq": 0.022914757103574702}, {"topic": "Accountability", "counts": 37, "freq": 0.01695692025664528}, {"topic": "Other", "counts": 158, "freq": 0.07241063244729606}]