[{"topic": "Economy", "counts": 7538, "freq": 0.22181679074831534}, {"topic": "Privatization", "counts": 4928, "freq": 0.14501368331224435}, {"topic": "Debt", "counts": 3944, "freq": 0.11605802901450725}, {"topic": "Energy", "counts": 3161, "freq": 0.09301709678368596}, {"topic": "Elections", "counts": 2957, "freq": 0.08701409528293559}, {"topic": "Corruption", "counts": 2124, "freq": 0.06250183915487155}, {"topic": "Democracy", "counts": 1976, "freq": 0.05814672041903304}, {"topic": "Media", "counts": 1117, "freq": 0.03286937586440279}, {"topic": "Environment", "counts": 759, "freq": 0.022334696760144778}, {"topic": "Education", "counts": 691, "freq": 0.020333696259894653}, {"topic": "Transparency", "counts": 615, "freq": 0.01809728393608569}, {"topic": "Housing", "counts": 546, "freq": 0.01606685695789071}, {"topic": "Europe", "counts": 524, "freq": 0.015419474443103905}, {"topic": "External affairs", "counts": 485, "freq": 0.01427184180325457}, {"topic": "Energy ", "counts": 312, "freq": 0.009181061118794692}, {"topic": "Privatization ", "counts": 293, "freq": 0.00862195803784245}, {"topic": "Human rights", "counts": 263, "freq": 0.007739163699496807}, {"topic": "Employment", "counts": 201, "freq": 0.00591472206691581}, {"topic": "Pensioners", "counts": 159, "freq": 0.00467880999323191}, {"topic": "Entrepreneurship", "counts": 156, "freq": 0.004590530559397346}, {"topic": "Migration", "counts": 132, "freq": 0.003884295088720831}, {"topic": "Other", "counts": 1102, "freq": 0.03242797869522997}]