[{"topic": "Elections", "subtopic": "Abstention", "counts": 199, "freq": 0.05217619297325642}, {"topic": "Elections", "subtopic": "Working class", "counts": 189, "freq": 0.049554273728369166}, {"topic": "Elections", "subtopic": "Other", "counts": 1168, "freq": 0.3062401678028317}, {"topic": "Employment", "subtopic": "Workers' rights", "counts": 632, "freq": 0.16570529627687466}, {"topic": "Employment", "subtopic": "Working class", "counts": 258, "freq": 0.06764551651809124}, {"topic": "Employment", "subtopic": "None", "counts": 117, "freq": 0.030676455165180912}, {"topic": "Employment", "subtopic": "Other", "counts": 344, "freq": 0.09019402202412166}, {"topic": "Economy", "subtopic": "Reforms", "counts": 113, "freq": 0.02962768746722601}, {"topic": "Economy", "subtopic": "Workers' rights", "counts": 110, "freq": 0.028841111693759833}, {"topic": "Health", "subtopic": "Public health system", "counts": 157, "freq": 0.04116413214472994}, {"topic": "Social state", "subtopic": "Other", "counts": 114, "freq": 0.029889879391714735}, {"topic": "Education", "subtopic": "Higher education", "counts": 103, "freq": 0.02700576822233875}, {"topic": "External affairs", "subtopic": "Other", "counts": 98, "freq": 0.025694808599895123}, {"topic": "Civil protection", "subtopic": "Other", "counts": 84, "freq": 0.02202412165705296}, {"topic": "Housing", "subtopic": "Other", "counts": 38, "freq": 0.009963293130571578}, {"topic": "Energy", "subtopic": "Other", "counts": 21, "freq": 0.00550603041426324}, {"topic": "Other", "subtopic": "Bank regulations", "counts": 69, "freq": 0.018091242789722076}]