[{"topic": "Elections", "subtopic": "Other", "sentiment": 0.5, "counts": 168}, {"topic": "Elections", "subtopic": "Other", "sentiment": 0.7, "counts": 179}, {"topic": "Elections", "subtopic": "Other", "sentiment": -0.5, "counts": 223}, {"topic": "Elections", "subtopic": "Other", "sentiment": 0.2, "counts": 196}, {"topic": "Elections", "subtopic": "Other", "sentiment": -0.2, "counts": 231}, {"topic": "Economy", "subtopic": "Other", "sentiment": -0.8, "counts": 102}, {"topic": "Privatization", "subtopic": "Privatization of healthcare", "sentiment": -0.7, "counts": 114}, {"topic": "Pandemic", "subtopic": "Public health system", "sentiment": -0.8, "counts": 42}, {"topic": "Health", "subtopic": "Public health system", "sentiment": -0.8, "counts": 98}, {"topic": "Health", "subtopic": "Other", "sentiment": -0.8, "counts": 208}, {"topic": "Health", "subtopic": "Privatization of healthcare", "sentiment": -0.8, "counts": 171}, {"topic": "Economy", "subtopic": "Tax cuts", "sentiment": -0.5, "counts": 183}, {"topic": "Housing", "subtopic": "Mortgages", "sentiment": -0.8, "counts": 127}, {"topic": "Elections", "subtopic": "Election spending", "sentiment": 0.2, "counts": 125}, {"topic": "Transparency", "subtopic": "Campaigning", "sentiment": -0.5, "counts": 86}, {"topic": "Debt", "subtopic": "Austerity", "sentiment": 0.4, "counts": 93}, {"topic": "Social state", "subtopic": "Other", "sentiment": 0.0, "counts": 103}, {"topic": "Elections", "subtopic": "Election spending", "sentiment": 0.8, "counts": 121}]