[{"topic": "Tourism", "subtopic": "Other", "counts": 784, "freq": 0.20258397932816538}, {"topic": "Entrepreneurship", "subtopic": "Employment", "counts": 158, "freq": 0.04082687338501292}, {"topic": "Entrepreneurship", "subtopic": "Economic equity", "counts": 141, "freq": 0.03643410852713178}, {"topic": "Entrepreneurship", "subtopic": "Investments", "counts": 121, "freq": 0.031266149870801035}, {"topic": "Entrepreneurship", "subtopic": "European recovery fund", "counts": 110, "freq": 0.028423772609819122}, {"topic": "Entrepreneurship", "subtopic": "Loans", "counts": 59, "freq": 0.01524547803617571}, {"topic": "Entrepreneurship", "subtopic": "Other", "counts": 171, "freq": 0.044186046511627906}, {"topic": "Employment", "subtopic": "Working class", "counts": 126, "freq": 0.03255813953488372}, {"topic": "Employment", "subtopic": "Workers' rights", "counts": 62, "freq": 0.016020671834625324}, {"topic": "Employment", "subtopic": "Other", "counts": 157, "freq": 0.040568475452196384}, {"topic": "Democracy", "subtopic": "Other", "counts": 291, "freq": 0.07519379844961241}, {"topic": "Elections", "subtopic": "Election spending", "counts": 102, "freq": 0.02635658914728682}, {"topic": "Elections", "subtopic": "Campaigning", "counts": 44, "freq": 0.011369509043927648}, {"topic": "Elections", "subtopic": "Other", "counts": 124, "freq": 0.03204134366925065}, {"topic": "Infrastructure", "subtopic": "Railway", "counts": 23, "freq": 0.005943152454780362}, {"topic": "Infrastructure", "subtopic": "Other", "counts": 208, "freq": 0.053746770025839795}, {"topic": "Economy", "subtopic": "European recovery fund", "counts": 61, "freq": 0.015762273901808784}, {"topic": "Economy", "subtopic": "Economic equity", "counts": 45, "freq": 0.011627906976744186}, {"topic": "Economy", "subtopic": "Tax cuts", "counts": 18, "freq": 0.004651162790697674}, {"topic": "Economy", "subtopic": "Other", "counts": 100, "freq": 0.025839793281653745}, {"topic": "Privatization", "subtopic": "Electricity", "counts": 91, "freq": 0.023514211886304908}, {"topic": "Privatization", "subtopic": "Other", "counts": 121, "freq": 0.031266149870801035}, {"topic": "Energy", "subtopic": "Green energy", "counts": 92, "freq": 0.023772609819121448}, {"topic": "Energy", "subtopic": "Energy crisis", "counts": 30, "freq": 0.007751937984496124}, {"topic": "Energy", "subtopic": "Other", "counts": 51, "freq": 0.01317829457364341}, {"topic": "Environment", "subtopic": "Other", "counts": 144, "freq": 0.037209302325581395}, {"topic": "Corruption", "subtopic": "None", "counts": 99, "freq": 0.02558139534883721}, {"topic": "Health", "subtopic": "Privatization of healthcare", "counts": 52, "freq": 0.013436692506459949}, {"topic": "Health", "subtopic": "Other", "counts": 38, "freq": 0.009819121447028423}, {"topic": "Transparency", "subtopic": "Inequality", "counts": 80, "freq": 0.020671834625323}, {"topic": "Debt", "subtopic": "Debt regulations", "counts": 47, "freq": 0.01214470284237726}, {"topic": "Debt", "subtopic": "Bankruptcy", "counts": 21, "freq": 0.005426356589147287}, {"topic": "Social state", "subtopic": "Other", "counts": 51, "freq": 0.01317829457364341}, {"topic": "Education", "subtopic": "Other", "counts": 48, "freq": 0.012403100775193798}]