[{"topic": "Economy", "counts": 2177, "freq": 0.36168798803788005}, {"topic": "Elections", "counts": 997, "freq": 0.16564213324472504}, {"topic": "Employment", "counts": 564, "freq": 0.09370327296893172}, {"topic": "Health", "counts": 445, "freq": 0.07393254693470676}, {"topic": "Privatization", "counts": 350, "freq": 0.05814919421830869}, {"topic": "Housing", "counts": 346, "freq": 0.057484631998670876}, {"topic": "Transparency", "counts": 271, "freq": 0.04502409038046187}, {"topic": "Education", "counts": 259, "freq": 0.04303040372154843}, {"topic": "Corruption", "counts": 242, "freq": 0.040206014288087726}, {"topic": "Democracy", "counts": 151, "freq": 0.025087223791327464}, {"topic": "Infrastructure", "counts": 86, "freq": 0.014288087722212992}, {"topic": "Energy", "counts": 85, "freq": 0.014121947167303538}, {"topic": "Pandemic", "counts": 46, "freq": 0.007642465525834856}]