[{"topic": "Other", "subtopic": "Other", "sentiment": 0.5}, {"topic": "Other", "subtopic": "Other", "sentiment": -0.6}, {"topic": "Elections", "subtopic": "Other", "sentiment": -0.3}, {"topic": "Corruption", "subtopic": "Corruption", "sentiment": -0.9}, {"topic": "Media", "subtopic": "Journalism", "sentiment": -0.8}, {"topic": "Democracy", "subtopic": "Other", "sentiment": 0.0}, {"topic": "Economy", "subtopic": "Hospital privatization", "sentiment": -0.5}, {"topic": "Employment", "subtopic": "Employment", "sentiment": -0.6}, {"topic": "Debt", "subtopic": "Debt regulations", "sentiment": -0.9}, {"topic": "Other", "subtopic": "None", "sentiment": -0.3}, {"topic": "Economy", "subtopic": "Other", "sentiment": 0.1}, {"topic": "Democracy", "subtopic": "Borders", "sentiment": -0.6}, {"topic": "Other", "subtopic": "Other", "sentiment": -0.4}, {"topic": "External affairs", "subtopic": "Other", "sentiment": -0.6}, {"topic": "Other", "subtopic": "Other", "sentiment": -0.6}, {"topic": "Agricultural policy", "subtopic": "Other", "sentiment": -0.45}, {"topic": "Economy", "subtopic": "Wind energy", "sentiment": 0.0}, {"topic": "Pensioners", "subtopic": "Pensions", "sentiment": -0.1}, {"topic": "Other", "subtopic": "Other", "sentiment": 0.0}, {"topic": "Accountability", "subtopic": "Other", "sentiment": -0.9}]