[{"topic": "Elections", "counts": 1627, "freq": 0.6311093871217999}, {"topic": "Agricultural policy", "counts": 198, "freq": 0.07680372381691233}, {"topic": "Housing", "counts": 160, "freq": 0.062063615205585725}, {"topic": "Justice", "counts": 101, "freq": 0.03917765709852599}, {"topic": "Human rights", "counts": 97, "freq": 0.03762606671838634}, {"topic": "Infrastructure", "counts": 94, "freq": 0.03646237393328161}, {"topic": "Health", "counts": 72, "freq": 0.027928626842513578}, {"topic": "Education", "counts": 39, "freq": 0.015128006206361521}, {"topic": "Economy", "counts": 32, "freq": 0.012412723041117145}, {"topic": "Other", "counts": 158, "freq": 0.0612878200155159}]